wetools/__init__.py
wetools/funcs.py
wetools-0.0.2.dist-info/METADATA
wetools-0.0.2.dist-info/WHEEL
wetools-0.0.2.dist-info/licenses/LICENSE
wetools-0.0.2.dist-info/RECORD
