Metadata-Version: 2.1
Name: wetools
Version: 0.0.2
Summary: Tools I use day to day
Project-URL: Homepage, https://github.com/williameaton/wetools
Author-email: W Eaton <weaton@princeton.edu>
License-File: LICENSE
Classifier: License :: OSI Approved :: MIT License
Classifier: Operating System :: OS Independent
Classifier: Programming Language :: Python :: 3
Requires-Python: >=3.7
Requires-Dist: numpy>=1.20.3
Requires-Dist: obspy>1.2
Requires-Dist: scipy>1.7
